bottle_jwt/__init__.py
bottle_jwt/bottle_jwt.py
bottle_jwt3-0.0.1.dist-info/LICENSE.txt
bottle_jwt3-0.0.1.dist-info/METADATA
bottle_jwt3-0.0.1.dist-info/WHEEL
bottle_jwt3-0.0.1.dist-info/top_level.txt
bottle_jwt3-0.0.1.dist-info/RECORD
