Metadata-Version: 2.1
Name: bottle-jwt3
Version: 0.0.1
Summary: JWT for Bottle
Author-email: TJ Renninger <renninger12@gmail.com>
Project-URL: repository, https://github.com/thepure12/bottle-jwt
Classifier: Programming Language :: Python :: 3
Classifier: License :: OSI Approved :: MIT License
Classifier: Operating System :: OS Independent
Requires-Python: >=3.8
License-File: LICENSE.txt
Requires-Dist: bottle
Requires-Dist: PyJWT
